mini_util/__init__.py
mini_util/cli.py
mini_util/do_after.py
mini_util/repeat_do.py
mini_util-0.1.12.dist-info/METADATA
mini_util-0.1.12.dist-info/WHEEL
mini_util-0.1.12.dist-info/entry_points.txt
mini_util-0.1.12.dist-info/RECORD
