Metadata-Version: 2.1
Name: mini-util
Version: 0.1.12
Summary: A minimalistic Python util library for some daily usage
Author: Harvey Tung
Author-email: haotingtong30@gmail.com
Requires-Python: >=3.10,<4.0
Classifier: Programming Language :: Python :: 3
Classifier: Programming Language :: Python :: 3.10
Classifier: Programming Language :: Python :: 3.11
Classifier: Programming Language :: Python :: 3.12
Requires-Dist: argparse (>=1.4.0,<2.0.0)
Project-URL: repository, https://github.com/i-am-harveyt/mini_util
